one/__init__.py
one/api.py
one/converters.py
one/params.py
one/registration.py
one/util.py
one/webclient.py
one/alf/__init__.py
one/alf/cache.py
one/alf/exceptions.py
one/alf/io.py
one/alf/path.py
one/alf/spec.py
one/remote/__init__.py
one/remote/aws.py
one/remote/base.py
one/remote/globus.py
one/tests/fixtures/datasets.pqt
one/tests/fixtures/sessions.pqt
one/tests/fixtures/test_dbs.json
one/tests/fixtures/test_img.png
one/tests/fixtures/params/.caches
one/tests/fixtures/params/.test.alyx.internationalbrainlab.org
one/tests/fixtures/rest_responses/1f187d80fd59677b395fcdb18e68e4401bfa1cc9
one/tests/fixtures/rest_responses/3f51aa2e0baa42438467906f56a457c91a221898
one/tests/fixtures/rest_responses/47893cf67c985e6361cdee009334963f49fb0746
one/tests/fixtures/rest_responses/535d0e9a1e2c1efbdeba0d673b131e00361a2edb
one/tests/fixtures/rest_responses/5618bea3484a52cd893616f07903f0e49e023ba1
one/tests/fixtures/rest_responses/6dc96f7e9bcc6ac2e7581489b9580a6cd3f28293
one/tests/fixtures/rest_responses/coreapi.json
one/tests/fixtures/rest_responses/db1731fb8df0208944ae85f76718430813a8bf50
one/tests/fixtures/rest_responses/dcce48259bb929661f60a02a48563f70aa6185b3
one/tests/fixtures/rest_responses/f530d6022f61cdc9e38cc66beb3cb71f3003c9a1
one/tests/fixtures/rest_responses/openapiv3.json
one_api-3.4.1.dist-info/licenses/LICENSE
one_api-3.4.1.dist-info/METADATA
one_api-3.4.1.dist-info/WHEEL
one_api-3.4.1.dist-info/top_level.txt
one_api-3.4.1.dist-info/RECORD
