Metadata-Version: 2.4
Name: ONE-api
Version: 3.4.1
Summary: Open Neurophysiology Environment
Author: IBL Staff
License: MIT
Project-URL: Homepage, https://github.com/int-brain-lab/ONE
Project-URL: Documentation, https://one.internationalbrainlab.org
Project-URL: Repository, https://github.com/int-brain-lab/ONE.git
Project-URL: Issues, https://github.com/int-brain-lab/ONE/issues
Project-URL: Changelog, https://github.com/int-brain-lab/ONE/blob/main/CHANGELOG.md
Requires-Python: >=3.10
License-File: LICENSE
Requires-Dist: ruff
Requires-Dist: numpy>=1.18
Requires-Dist: pandas>=1.5.0
Requires-Dist: tqdm>=4.32.1
Requires-Dist: requests>=2.22.0
Requires-Dist: iblutil>=1.14.0
Requires-Dist: packaging
Requires-Dist: boto3
Requires-Dist: pyyaml
Dynamic: license-file
